LICENSE
MANIFEST.in
README.md
setup.py
nbtermix/__init__.py
nbtermix/_version.py
nbtermix/cell.py
nbtermix/format.py
nbtermix/help.py
nbtermix/key_bindings.py
nbtermix/log.py
nbtermix/nbterm.py
nbtermix/notebook.py
nbtermix.egg-info/PKG-INFO
nbtermix.egg-info/SOURCES.txt
nbtermix.egg-info/dependency_links.txt
nbtermix.egg-info/entry_points.txt
nbtermix.egg-info/requires.txt
nbtermix.egg-info/top_level.txt