Metadata-Version: 2.1
Name: nbtermix
Version: 0.1.5
Summary: Jupyter Notebook in Your Terminal
Home-page: https://github.com/mtatton/nbterm
Author: Michael Tatton
License: UNKNOWN
Platform: UNKNOWN
Classifier: Programming Language :: Python :: 3
Classifier: License :: OSI Approved :: MIT License
Classifier: Operating System :: OS Independent
Requires-Python: >=3.7
Provides-Extra: test
License-File: LICENSE
